Metadata-Version: 2.4
Name: llama-index-vector-stores-couchbase
Version: 0.5.1
Summary: llama-index vector_stores couchbase integration
Author-email: Couchbase <devadvocates@couchbase.com>
License-Expression: MIT
License-File: LICENSE
Requires-Python: <4.0,>=3.9
Requires-Dist: couchbase<5,>=4.2.0
Requires-Dist: llama-index-core<0.15,>=0.13.0
Requires-Dist: llama-index-embeddings-openai<0.6,>=0.5.0
